CHANGELOG.md
LICENSE
README.md
django_rest_typescript_generator/__init__.py
django_rest_typescript_generator/apps.py
django_rest_typescript_generator/build.py
django_rest_typescript_generator/management/__init__.py
django_rest_typescript_generator/management/commands/__init__.py
django_rest_typescript_generator/management/commands/buildtypescript.py
django_rest_typescript_generator/py.typed
django_rest_typescript_generator/templates.py
django_rest_typescript_generator/typescript.py
django_rest_typescript_generator-0.0.2.dist-info/LICENSE
django_rest_typescript_generator-0.0.2.dist-info/METADATA
django_rest_typescript_generator-0.0.2.dist-info/WHEEL
django_rest_typescript_generator-0.0.2.dist-info/RECORD
